{
  "kind": "collectionType",
  "collectionName": "process_steps",
  "info": {
    "singularName": "process-step",
    "pluralName": "process-steps",
    "displayName": "Process Step",
    "description": "Steps in the Axerate process"
  },
  "options": {
    "draftAndPublish": true
  },
  "pluginOptions": {},
  "attributes": {
    "icon": {
      "type": "string",
      "required": true
    },
    "title": {
      "type": "string",
      "required": true
    },
    "description": {
      "type": "text",
      "required": true
    },
    "order": {
      "type": "integer",
      "default": 0
    },
    "page": {
      "type": "enumeration",
      "enum": ["main", "startup"],
      "default": "main",
      "required": true
    }
  }
}
